pydemod/__init__.py
pydemod/app/__init__.py
pydemod/app/amss.py
pydemod/app/rds.py
pydemod/app/weather_sensors.py
pydemod/coding/__init__.py
pydemod/coding/crc.py
pydemod/coding/logic.py
pydemod/coding/manchester.py
pydemod/coding/polynomial.py
pydemod/filters/__init__.py
pydemod/filters/shaping.py
pydemod/modulation/__init__.py
pydemod/modulation/am.py
pydemod/modulation/phase.py
pydemod-1.5.dist-info/METADATA
pydemod-1.5.dist-info/WHEEL
pydemod-1.5.dist-info/top_level.txt
pydemod-1.5.dist-info/RECORD
