Metadata-Version: 2.1
Name: pydemod
Version: 1.5
Summary: Python modulation library
Home-page: https://flerken.zapto.org:1115/kuba/Pydemod
Author: kuba201
Project-URL: Source, https://flerken.zapto.org:1115/kuba/Pydemod
Keywords: radiodatasystem,rds,amss,am
Classifier: Intended Audience :: Education
Classifier: Intended Audience :: Telecommunications Industry
Classifier: Programming Language :: Python :: 3 :: Only
Classifier: Programming Language :: Python :: 3.10
